img_convert/__init__.py
img_convert/main_test.py
img_convert/utils/__init__.py
img_convert/utils/io.py
img_convert-0.0.1.dist-info/METADATA
img_convert-0.0.1.dist-info/WHEEL
img_convert-0.0.1.dist-info/top_level.txt
img_convert-0.0.1.dist-info/RECORD
