Metadata-Version: 2.1
Name: img-convert
Version: 0.0.1
Summary: Projeto para conversao de imagem RGB.
Home-page: https://github.com/ceconelo
Author: Thiago Oliveira
Author-email: thiceconelo@gmail.com
License: MIT
Platform: UNKNOWN
Requires-Dist: opencv-python
Requires-Dist: numpy
